eAsisitentAPI/__init__.py
eAsisitentAPI/pharser.py
eAsisitentAPI/scraper.py
eAsistentAPI-2.0.0.dist-info/LICENSE
eAsistentAPI-2.0.0.dist-info/METADATA
eAsistentAPI-2.0.0.dist-info/WHEEL
eAsistentAPI-2.0.0.dist-info/top_level.txt
eAsistentAPI-2.0.0.dist-info/RECORD
